{
  "type": "FeatureCollection",
  "features": [
    {
      "type": "Feature",
      "geometry": {
        "type": "Point",
        "coordinates": [
          -71.5023,
          43.2027
        ]
      },
      "properties": {
        "name": "Black Hawks (151st Aviation / AASF)",
        "side": "E",
        "category": "military_air",
        "note": "UH-60 Black Hawks at the Army Aviation Support Facility, Concord Municipal Airport. Includes 238th MEDEVAC."
      }
    }
  ]
}