{"type": "FeatureCollection", "features": [{"type": "Feature", "geometry": {"type": "Point", "coordinates": [-71.50944, 43.16552]}, "properties": {"name": "Garvins Falls hydro (12.4 MW)", "side": "Contested", "category": "power_gen", "note": "Mid-river hydroelectric on the Bow/Concord line; 12.4 MW across 4 units. Owner LS Power / Patriot Hydro (formerly Hull Street Energy, sold 2023). The contested generator - the river itself.", "source_url": "https://www.gridinfo.com/plant/garvins-falls/2357"}}]}