{
"type": "FeatureCollection",
"name": "resources_fortress",
"crs": { "type": "name", "properties": { "name": "urn:ogc:def:crs:OGC:1.3:CRS84" } },
"features": [
{ "type": "Feature", "properties": { "name": "Steeplegate Mall (fortress)", "category": "fortress", "side": "E", "actual_side": "E", "note": "dead megastructure -> barracks/staging", "src": "census" }, "geometry": { "type": "Point", "coordinates": [ -71.492343662378005, 43.222858308143998 ] } }
]
}
