{
"type": "FeatureCollection",
"name": "resources_govt",
"crs": { "type": "name", "properties": { "name": "urn:ogc:def:crs:OGC:1.3:CRS84" } },
"features": [
{ "type": "Feature", "properties": { "name": "NH State House", "category": "govt", "side": "W", "actual_side": "W", "note": "seat of government", "src": "census" }, "geometry": { "type": "Point", "coordinates": [ -71.537632310058015, 43.209975980148002 ] } }
]
}
